laifen/__init__.py
laifen/calculator.py
laifen-1.0.0.dist-info/METADATA
laifen-1.0.0.dist-info/WHEEL
laifen-1.0.0.dist-info/top_level.txt
laifen-1.0.0.dist-info/RECORD
