Metadata-Version: 2.1
Name: laifen
Version: 1.0.0
Summary: A simple package for addition within 100.
Author: laifen
Author-email: your.email@example.com
